Topsis/__init__.py
Topsis/topsis.py
topsis_harshtyagi_102203964-1.0.0.dist-info/LICENCE.txt
topsis_harshtyagi_102203964-1.0.0.dist-info/METADATA
topsis_harshtyagi_102203964-1.0.0.dist-info/WHEEL
topsis_harshtyagi_102203964-1.0.0.dist-info/top_level.txt
topsis_harshtyagi_102203964-1.0.0.dist-info/RECORD
