Metadata-Version: 2.2
Name: topsis_harshtyagi_102203964
Version: 1.0.0
Summary: A Python implementation of the TOPSIS method for multi-criteria decision making.
Home-page: https://github.com/harshtyagi102203964/topsis
Author: Harsh Tyagi
Author-email: htyagi_be22@thapar.edu
Classifier: Programming Language :: Python :: 3
Classifier: License :: OSI Approved :: MIT License
Classifier: Operating System :: OS Independent
Requires-Python: >=3.6
License-File: LICENCE.txt
Dynamic: author
Dynamic: author-email
Dynamic: classifier
Dynamic: description
Dynamic: description-content-type
Dynamic: home-page
Dynamic: requires-python
Dynamic: summary
